{
  "alignment_summary": {
    "matched_defined": 22,
    "matched_undefined": 2,
    "regime_labels_unavailable": 0,
    "total_rows": 24,
    "unmatched_timestamp": 0
  },
  "artifact_type": "regime_attribution_summary",
  "best_regime": {
    "coverage_status": "sufficient",
    "metric_value": 0.037500000000000006,
    "observation_count": 2,
    "regime_label": "volatility=low_volatility|trend=downtrend|drawdown_recovery=drawdown|stress=correlation_stress"
  },
  "coverage_caveats": [
    "one or more regimes are sparse and carry null metrics",
    "matched_undefined rows were excluded from attribution"
  ],
  "coverage_counts": {
    "sparse": 12,
    "sufficient": 5
  },
  "dimension": "composite",
  "dominant_regime_label": "volatility=low_volatility|trend=downtrend|drawdown_recovery=drawdown|stress=correlation_stress",
  "dominant_regime_metric": 0.037500000000000006,
  "dominant_regime_share": 0.3488372093023256,
  "empty_regime_count": 0,
  "fragility_flag": false,
  "fragility_reason": "no deterministic fragility heuristic triggered",
  "interpretation_highlights": [
    "Best mean_ic came from `volatility=low_volatility|trend=downtrend|drawdown_recovery=drawdown|stress=correlation_stress` at 0.0375.",
    "Weakest regime was `volatility=low_volatility|trend=uptrend|drawdown_recovery=recovery|stress=correlation_stress` at 0.0150.",
    "Positive contribution is led by `volatility=low_volatility|trend=downtrend|drawdown_recovery=drawdown|stress=correlation_stress` with share 0.3488.",
    "Fragility heuristic: no deterministic fragility heuristic triggered."
  ],
  "metadata": {
    "alpha_variant": "defensive",
    "case_study_surface": "alpha_defensive",
    "surface": "alpha"
  },
  "metric_columns": [
    "regime_label",
    "dimension",
    "observation_count",
    "coverage_status",
    "mean_ic",
    "mean_rank_ic",
    "ic_std",
    "rank_ic_std",
    "ic_ir",
    "rank_ic_ir"
  ],
  "metric_direction": "desc",
  "negative_regime_count": 0,
  "positive_regime_count": 5,
  "primary_metric": "mean_ic",
  "regime_concentration_score": 0.2309356408869659,
  "regime_count": 17,
  "regimes": [
    {
      "absolute_contribution_share": null,
      "contribution_sign": "undefined",
      "coverage_caveat": "regime has fewer than min_observations rows",
      "coverage_status": "sparse",
      "dimension": "composite",
      "evidence_warning": "sparse_evidence",
      "ic_ir": null,
      "ic_std": null,
      "is_best_regime": false,
      "is_worst_regime": false,
      "mean_ic": null,
      "mean_rank_ic": null,
      "metric_direction": "desc",
      "metric_rank": null,
      "observation_count": 1,
      "positive_contribution_share": null,
      "primary_metric": "mean_ic",
      "primary_metric_value": null,
      "rank_ic_ir": null,
      "rank_ic_std": null,
      "regime_label": "volatility=high_volatility|trend=downtrend|drawdown_recovery=recovery|stress=correlation_stress",
      "surface": "alpha"
    },
    {
      "absolute_contribution_share": null,
      "contribution_sign": "undefined",
      "coverage_caveat": "regime has fewer than min_observations rows",
      "coverage_status": "sparse",
      "dimension": "composite",
      "evidence_warning": "sparse_evidence",
      "ic_ir": null,
      "ic_std": null,
      "is_best_regime": false,
      "is_worst_regime": false,
      "mean_ic": null,
      "mean_rank_ic": null,
      "metric_direction": "desc",
      "metric_rank": null,
      "observation_count": 1,
      "positive_contribution_share": null,
      "primary_metric": "mean_ic",
      "primary_metric_value": null,
      "rank_ic_ir": null,
      "rank_ic_std": null,
      "regime_label": "volatility=high_volatility|trend=downtrend|drawdown_recovery=underwater|stress=correlation_stress",
      "surface": "alpha"
    },
    {
      "absolute_contribution_share": 0.1395348837209302,
      "contribution_sign": "positive",
      "coverage_caveat": null,
      "coverage_status": "sufficient",
      "dimension": "composite",
      "evidence_warning": null,
      "ic_ir": 2.1213203435596424,
      "ic_std": 0.007071067811865475,
      "is_best_regime": false,
      "is_worst_regime": false,
      "mean_ic": 0.015,
      "mean_rank_ic": 0.022,
      "metric_direction": "desc",
      "metric_rank": 4.0,
      "observation_count": 2,
      "positive_contribution_share": 0.1395348837209302,
      "primary_metric": "mean_ic",
      "primary_metric_value": 0.015,
      "rank_ic_ir": 3.8890872965260113,
      "rank_ic_std": 0.00565685424949238,
      "regime_label": "volatility=high_volatility|trend=sideways|drawdown_recovery=recovery|stress=correlation_stress",
      "surface": "alpha"
    },
    {
      "absolute_contribution_share": null,
      "contribution_sign": "undefined",
      "coverage_caveat": "regime has fewer than min_observations rows",
      "coverage_status": "sparse",
      "dimension": "composite",
      "evidence_warning": "sparse_evidence",
      "ic_ir": null,
      "ic_std": null,
      "is_best_regime": false,
      "is_worst_regime": false,
      "mean_ic": null,
      "mean_rank_ic": null,
      "metric_direction": "desc",
      "metric_rank": null,
      "observation_count": 1,
      "positive_contribution_share": null,
      "primary_metric": "mean_ic",
      "primary_metric_value": null,
      "rank_ic_ir": null,
      "rank_ic_std": null,
      "regime_label": "volatility=high_volatility|trend=sideways|drawdown_recovery=underwater|stress=correlation_stress",
      "surface": "alpha"
    },
    {
      "absolute_contribution_share": null,
      "contribution_sign": "undefined",
      "coverage_caveat": "regime has fewer than min_observations rows",
      "coverage_status": "sparse",
      "dimension": "composite",
      "evidence_warning": "sparse_evidence",
      "ic_ir": null,
      "ic_std": null,
      "is_best_regime": false,
      "is_worst_regime": false,
      "mean_ic": null,
      "mean_rank_ic": null,
      "metric_direction": "desc",
      "metric_rank": null,
      "observation_count": 1,
      "positive_contribution_share": null,
      "primary_metric": "mean_ic",
      "primary_metric_value": null,
      "rank_ic_ir": null,
      "rank_ic_std": null,
      "regime_label": "volatility=high_volatility|trend=uptrend|drawdown_recovery=recovery|stress=correlation_stress",
      "surface": "alpha"
    },
    {
      "absolute_contribution_share": null,
      "contribution_sign": "undefined",
      "coverage_caveat": "regime has fewer than min_observations rows",
      "coverage_status": "sparse",
      "dimension": "composite",
      "evidence_warning": "sparse_evidence",
      "ic_ir": null,
      "ic_std": null,
      "is_best_regime": false,
      "is_worst_regime": false,
      "mean_ic": null,
      "mean_rank_ic": null,
      "metric_direction": "desc",
      "metric_rank": null,
      "observation_count": 1,
      "positive_contribution_share": null,
      "primary_metric": "mean_ic",
      "primary_metric_value": null,
      "rank_ic_ir": null,
      "rank_ic_std": null,
      "regime_label": "volatility=high_volatility|trend=uptrend|drawdown_recovery=underwater|stress=correlation_stress",
      "surface": "alpha"
    },
    {
      "absolute_contribution_share": 0.3488372093023256,
      "contribution_sign": "positive",
      "coverage_caveat": null,
      "coverage_status": "sufficient",
      "dimension": "composite",
      "evidence_warning": null,
      "ic_ir": 10.60660171779822,
      "ic_std": 0.003535533905932736,
      "is_best_regime": true,
      "is_worst_regime": false,
      "mean_ic": 0.037500000000000006,
      "mean_rank_ic": 0.0475,
      "metric_direction": "desc",
      "metric_rank": 1.0,
      "observation_count": 2,
      "positive_contribution_share": 0.3488372093023256,
      "primary_metric": "mean_ic",
      "primary_metric_value": 0.037500000000000006,
      "rank_ic_ir": 13.43502884254439,
      "rank_ic_std": 0.0035355339059327407,
      "regime_label": "volatility=low_volatility|trend=downtrend|drawdown_recovery=drawdown|stress=correlation_stress",
      "surface": "alpha"
    },
    {
      "absolute_contribution_share": 0.1627906976744186,
      "contribution_sign": "positive",
      "coverage_caveat": null,
      "coverage_status": "sufficient",
      "dimension": "composite",
      "evidence_warning": null,
      "ic_ir": 4.949747468305832,
      "ic_std": 0.0035355339059327385,
      "is_best_regime": false,
      "is_worst_regime": false,
      "mean_ic": 0.0175,
      "mean_rank_ic": 0.025,
      "metric_direction": "desc",
      "metric_rank": 3.0,
      "observation_count": 2,
      "positive_contribution_share": 0.1627906976744186,
      "primary_metric": "mean_ic",
      "primary_metric_value": 0.0175,
      "rank_ic_ir": 5.8925565098878945,
      "rank_ic_std": 0.004242640687119287,
      "regime_label": "volatility=low_volatility|trend=sideways|drawdown_recovery=near_peak|stress=correlation_stress",
      "surface": "alpha"
    },
    {
      "absolute_contribution_share": null,
      "contribution_sign": "undefined",
      "coverage_caveat": "regime has fewer than min_observations rows",
      "coverage_status": "sparse",
      "dimension": "composite",
      "evidence_warning": "sparse_evidence",
      "ic_ir": null,
      "ic_std": null,
      "is_best_regime": false,
      "is_worst_regime": false,
      "mean_ic": null,
      "mean_rank_ic": null,
      "metric_direction": "desc",
      "metric_rank": null,
      "observation_count": 1,
      "positive_contribution_share": null,
      "primary_metric": "mean_ic",
      "primary_metric_value": null,
      "rank_ic_ir": null,
      "rank_ic_std": null,
      "regime_label": "volatility=low_volatility|trend=sideways|drawdown_recovery=recovery|stress=dispersion_stress",
      "surface": "alpha"
    },
    {
      "absolute_contribution_share": 0.1395348837209302,
      "contribution_sign": "positive",
      "coverage_caveat": null,
      "coverage_status": "sufficient",
      "dimension": "composite",
      "evidence_warning": null,
      "ic_ir": null,
      "ic_std": 0.0,
      "is_best_regime": false,
      "is_worst_regime": true,
      "mean_ic": 0.015,
      "mean_rank_ic": 0.0225,
      "metric_direction": "desc",
      "metric_rank": 5.0,
      "observation_count": 2,
      "positive_contribution_share": 0.1395348837209302,
      "primary_metric": "mean_ic",
      "primary_metric_value": 0.015,
      "rank_ic_ir": 10.606601717798215,
      "rank_ic_std": 0.002121320343559642,
      "regime_label": "volatility=low_volatility|trend=uptrend|drawdown_recovery=recovery|stress=correlation_stress",
      "surface": "alpha"
    },
    {
      "absolute_contribution_share": 0.2093023255813953,
      "contribution_sign": "positive",
      "coverage_caveat": null,
      "coverage_status": "sufficient",
      "dimension": "composite",
      "evidence_warning": null,
      "ic_ir": 6.363961030678926,
      "ic_std": 0.0035355339059327385,
      "is_best_regime": false,
      "is_worst_regime": false,
      "mean_ic": 0.0225,
      "mean_rank_ic": 0.0325,
      "metric_direction": "desc",
      "metric_rank": 2.0,
      "observation_count": 2,
      "positive_contribution_share": 0.2093023255813953,
      "primary_metric": "mean_ic",
      "primary_metric_value": 0.0225,
      "rank_ic_ir": 9.19238815542511,
      "rank_ic_std": 0.0035355339059327407,
      "regime_label": "volatility=normal_volatility|trend=downtrend|drawdown_recovery=drawdown|stress=correlation_stress",
      "surface": "alpha"
    },
    {
      "absolute_contribution_share": null,
      "contribution_sign": "undefined",
      "coverage_caveat": "regime has fewer than min_observations rows",
      "coverage_status": "sparse",
      "dimension": "composite",
      "evidence_warning": "sparse_evidence",
      "ic_ir": null,
      "ic_std": null,
      "is_best_regime": false,
      "is_worst_regime": false,
      "mean_ic": null,
      "mean_rank_ic": null,
      "metric_direction": "desc",
      "metric_rank": null,
      "observation_count": 1,
      "positive_contribution_share": null,
      "primary_metric": "mean_ic",
      "primary_metric_value": null,
      "rank_ic_ir": null,
      "rank_ic_std": null,
      "regime_label": "volatility=normal_volatility|trend=sideways|drawdown_recovery=underwater|stress=correlation_stress",
      "surface": "alpha"
    },
    {
      "absolute_contribution_share": null,
      "contribution_sign": "undefined",
      "coverage_caveat": "regime has fewer than min_observations rows",
      "coverage_status": "sparse",
      "dimension": "composite",
      "evidence_warning": "sparse_evidence",
      "ic_ir": null,
      "ic_std": null,
      "is_best_regime": false,
      "is_worst_regime": false,
      "mean_ic": null,
      "mean_rank_ic": null,
      "metric_direction": "desc",
      "metric_rank": null,
      "observation_count": 1,
      "positive_contribution_share": null,
      "primary_metric": "mean_ic",
      "primary_metric_value": null,
      "rank_ic_ir": null,
      "rank_ic_std": null,
      "regime_label": "volatility=normal_volatility|trend=uptrend|drawdown_recovery=near_peak|stress=correlation_stress",
      "surface": "alpha"
    },
    {
      "absolute_contribution_share": null,
      "contribution_sign": "undefined",
      "coverage_caveat": "regime has fewer than min_observations rows",
      "coverage_status": "sparse",
      "dimension": "composite",
      "evidence_warning": "sparse_evidence",
      "ic_ir": null,
      "ic_std": null,
      "is_best_regime": false,
      "is_worst_regime": false,
      "mean_ic": null,
      "mean_rank_ic": null,
      "metric_direction": "desc",
      "metric_rank": null,
      "observation_count": 1,
      "positive_contribution_share": null,
      "primary_metric": "mean_ic",
      "primary_metric_value": null,
      "rank_ic_ir": null,
      "rank_ic_std": null,
      "regime_label": "volatility=normal_volatility|trend=uptrend|drawdown_recovery=recovery|stress=correlation_stress",
      "surface": "alpha"
    },
    {
      "absolute_contribution_share": null,
      "contribution_sign": "undefined",
      "coverage_caveat": "regime has fewer than min_observations rows",
      "coverage_status": "sparse",
      "dimension": "composite",
      "evidence_warning": "sparse_evidence",
      "ic_ir": null,
      "ic_std": null,
      "is_best_regime": false,
      "is_worst_regime": false,
      "mean_ic": null,
      "mean_rank_ic": null,
      "metric_direction": "desc",
      "metric_rank": null,
      "observation_count": 1,
      "positive_contribution_share": null,
      "primary_metric": "mean_ic",
      "primary_metric_value": null,
      "rank_ic_ir": null,
      "rank_ic_std": null,
      "regime_label": "volatility=normal_volatility|trend=uptrend|drawdown_recovery=recovery|stress=dispersion_stress",
      "surface": "alpha"
    },
    {
      "absolute_contribution_share": null,
      "contribution_sign": "undefined",
      "coverage_caveat": "regime has fewer than min_observations rows",
      "coverage_status": "sparse",
      "dimension": "composite",
      "evidence_warning": "sparse_evidence",
      "ic_ir": null,
      "ic_std": null,
      "is_best_regime": false,
      "is_worst_regime": false,
      "mean_ic": null,
      "mean_rank_ic": null,
      "metric_direction": "desc",
      "metric_rank": null,
      "observation_count": 1,
      "positive_contribution_share": null,
      "primary_metric": "mean_ic",
      "primary_metric_value": null,
      "rank_ic_ir": null,
      "rank_ic_std": null,
      "regime_label": "volatility=normal_volatility|trend=uptrend|drawdown_recovery=underwater|stress=correlation_stress",
      "surface": "alpha"
    },
    {
      "absolute_contribution_share": null,
      "contribution_sign": "undefined",
      "coverage_caveat": "regime has fewer than min_observations rows",
      "coverage_status": "sparse",
      "dimension": "composite",
      "evidence_warning": "sparse_evidence",
      "ic_ir": null,
      "ic_std": null,
      "is_best_regime": false,
      "is_worst_regime": false,
      "mean_ic": null,
      "mean_rank_ic": null,
      "metric_direction": "desc",
      "metric_rank": null,
      "observation_count": 1,
      "positive_contribution_share": null,
      "primary_metric": "mean_ic",
      "primary_metric_value": null,
      "rank_ic_ir": null,
      "rank_ic_std": null,
      "regime_label": "volatility=normal_volatility|trend=uptrend|drawdown_recovery=underwater|stress=dispersion_stress",
      "surface": "alpha"
    }
  ],
  "run_id": "alpha_defensive_bundle",
  "schema_version": 1,
  "sparse_regime_count": 12,
  "sufficient_regime_count": 5,
  "surface": "alpha",
  "taxonomy_version": "regime_taxonomy_v1",
  "transition_summary": {
    "artifact_type": "regime_transition_attribution_summary",
    "best_transition_category": {
      "event_count": 5,
      "metric_value": 0.03075,
      "transition_category": "generic_transition",
      "transition_dimension": "drawdown_recovery"
    },
    "coverage_counts": {
      "sparse": 2,
      "sufficient": 33
    },
    "degradation_categories": [
      "drawdown_onset",
      "generic_transition",
      "generic_transition",
      "generic_transition",
      "recovery_onset",
      "trend_breakdown",
      "volatility_downshift",
      "volatility_upshift"
    ],
    "event_count": 35,
    "interpretation_highlights": [
      "Best transition category was `generic_transition` at 0.0307.",
      "Worst transition category was `recovery_onset` at 0.0173.",
      "Sparse transition categories: `generic_transition`, `volatility_upshift`."
    ],
    "metadata": {
      "case_study": "m24_7_regime_aware_case_study",
      "case_study_surface": "alpha_defensive",
      "min_observations": 2,
      "regime_prefix": "regime_",
      "surface": "alpha",
      "taxonomy_version": "regime_taxonomy_v1",
      "window": {
        "allow_window_overlap": true,
        "post_event_rows": 1,
        "pre_event_rows": 1
      }
    },
    "primary_metric": "post_mean_ic",
    "run_id": "alpha_defensive",
    "schema_version": 1,
    "sparse_transition_categories": [
      "generic_transition",
      "volatility_upshift"
    ],
    "stress_onset_summary": {
      "present": false,
      "transition_category": "stress_onset"
    },
    "surface": "alpha",
    "taxonomy_version": "regime_taxonomy_v1",
    "transition_categories": [
      {
        "adverse_event_count": 0,
        "average_event_mean_ic": 0.037500000000000006,
        "average_event_mean_rank_ic": 0.0475,
        "average_post_mean_ic": 0.0215,
        "average_post_mean_rank_ic": 0.029500000000000002,
        "average_pre_mean_ic": 0.0325,
        "average_pre_mean_rank_ic": 0.042499999999999996,
        "average_window_mean_ic": 0.0305,
        "average_window_mean_rank_ic": 0.03983333333333333,
        "degradation_event_count": 2,
        "empty_event_count": 0,
        "event_count": 2,
        "metric_rank": 5,
        "primary_metric": "post_mean_ic",
        "primary_metric_value": 0.0215,
        "sparse_event_count": 0,
        "sparse_warning": false,
        "sufficient_event_count": 2,
        "surface": "alpha",
        "transition_category": "drawdown_onset",
        "transition_dimension": "drawdown_recovery"
      },
      {
        "adverse_event_count": 0,
        "average_event_mean_ic": 0.020999999999999998,
        "average_event_mean_rank_ic": 0.029199999999999997,
        "average_post_mean_ic": 0.03075,
        "average_post_mean_rank_ic": 0.040249999999999994,
        "average_pre_mean_ic": 0.0196,
        "average_pre_mean_rank_ic": 0.026199999999999994,
        "average_window_mean_ic": 0.022633333333333335,
        "average_window_mean_rank_ic": 0.0305,
        "degradation_event_count": 1,
        "empty_event_count": 0,
        "event_count": 5,
        "metric_rank": 1,
        "primary_metric": "post_mean_ic",
        "primary_metric_value": 0.03075,
        "sparse_event_count": 1,
        "sparse_warning": true,
        "sufficient_event_count": 4,
        "surface": "alpha",
        "transition_category": "generic_transition",
        "transition_dimension": "drawdown_recovery"
      },
      {
        "adverse_event_count": 0,
        "average_event_mean_ic": 0.0215,
        "average_event_mean_rank_ic": 0.029,
        "average_post_mean_ic": 0.028999999999999998,
        "average_post_mean_rank_ic": 0.038,
        "average_pre_mean_ic": 0.025,
        "average_pre_mean_rank_ic": 0.032,
        "average_window_mean_ic": 0.02516666666666667,
        "average_window_mean_rank_ic": 0.033,
        "degradation_event_count": 1,
        "empty_event_count": 0,
        "event_count": 2,
        "metric_rank": 2,
        "primary_metric": "post_mean_ic",
        "primary_metric_value": 0.028999999999999998,
        "sparse_event_count": 0,
        "sparse_warning": false,
        "sufficient_event_count": 2,
        "surface": "alpha",
        "transition_category": "generic_transition",
        "transition_dimension": "stress"
      },
      {
        "adverse_event_count": 0,
        "average_event_mean_ic": 0.02,
        "average_event_mean_rank_ic": 0.027428571428571424,
        "average_post_mean_ic": 0.018857142857142857,
        "average_post_mean_rank_ic": 0.02614285714285714,
        "average_pre_mean_ic": 0.02157142857142857,
        "average_pre_mean_rank_ic": 0.029714285714285714,
        "average_window_mean_ic": 0.020142857142857146,
        "average_window_mean_rank_ic": 0.027761904761904762,
        "degradation_event_count": 5,
        "empty_event_count": 0,
        "event_count": 7,
        "metric_rank": 7,
        "primary_metric": "post_mean_ic",
        "primary_metric_value": 0.018857142857142857,
        "sparse_event_count": 0,
        "sparse_warning": false,
        "sufficient_event_count": 7,
        "surface": "alpha",
        "transition_category": "generic_transition",
        "transition_dimension": "trend"
      },
      {
        "adverse_event_count": 0,
        "average_event_mean_ic": 0.018666666666666665,
        "average_event_mean_rank_ic": 0.025999999999999995,
        "average_post_mean_ic": 0.017333333333333336,
        "average_post_mean_rank_ic": 0.023999999999999997,
        "average_pre_mean_ic": 0.028333333333333332,
        "average_pre_mean_rank_ic": 0.038,
        "average_window_mean_ic": 0.021444444444444443,
        "average_window_mean_rank_ic": 0.029333333333333333,
        "degradation_event_count": 3,
        "empty_event_count": 0,
        "event_count": 3,
        "metric_rank": 8,
        "primary_metric": "post_mean_ic",
        "primary_metric_value": 0.017333333333333336,
        "sparse_event_count": 0,
        "sparse_warning": false,
        "sufficient_event_count": 3,
        "surface": "alpha",
        "transition_category": "recovery_onset",
        "transition_dimension": "drawdown_recovery"
      },
      {
        "adverse_event_count": 0,
        "average_event_mean_ic": 0.035,
        "average_event_mean_rank_ic": 0.045,
        "average_post_mean_ic": 0.026500000000000003,
        "average_post_mean_rank_ic": 0.0345,
        "average_pre_mean_ic": 0.027500000000000004,
        "average_pre_mean_rank_ic": 0.0375,
        "average_window_mean_ic": 0.029666666666666668,
        "average_window_mean_rank_ic": 0.039,
        "degradation_event_count": 1,
        "empty_event_count": 0,
        "event_count": 2,
        "metric_rank": 3,
        "primary_metric": "post_mean_ic",
        "primary_metric_value": 0.026500000000000003,
        "sparse_event_count": 0,
        "sparse_warning": false,
        "sufficient_event_count": 2,
        "surface": "alpha",
        "transition_category": "trend_breakdown",
        "transition_dimension": "trend"
      },
      {
        "adverse_event_count": 0,
        "average_event_mean_ic": 0.026600000000000002,
        "average_event_mean_rank_ic": 0.0352,
        "average_post_mean_ic": 0.020999999999999998,
        "average_post_mean_rank_ic": 0.028199999999999996,
        "average_pre_mean_ic": 0.0244,
        "average_pre_mean_rank_ic": 0.033,
        "average_window_mean_ic": 0.024,
        "average_window_mean_rank_ic": 0.03213333333333333,
        "degradation_event_count": 4,
        "empty_event_count": 0,
        "event_count": 5,
        "metric_rank": 6,
        "primary_metric": "post_mean_ic",
        "primary_metric_value": 0.020999999999999998,
        "sparse_event_count": 0,
        "sparse_warning": false,
        "sufficient_event_count": 5,
        "surface": "alpha",
        "transition_category": "volatility_downshift",
        "transition_dimension": "volatility"
      },
      {
        "adverse_event_count": 0,
        "average_event_mean_ic": 0.021666666666666667,
        "average_event_mean_rank_ic": 0.029888888888888892,
        "average_post_mean_ic": 0.024375,
        "average_post_mean_rank_ic": 0.033,
        "average_pre_mean_ic": 0.02288888888888889,
        "average_pre_mean_rank_ic": 0.03133333333333334,
        "average_window_mean_ic": 0.022574074074074076,
        "average_window_mean_rank_ic": 0.030907407407407415,
        "degradation_event_count": 4,
        "empty_event_count": 0,
        "event_count": 9,
        "metric_rank": 4,
        "primary_metric": "post_mean_ic",
        "primary_metric_value": 0.024375,
        "sparse_event_count": 1,
        "sparse_warning": true,
        "sufficient_event_count": 8,
        "surface": "alpha",
        "transition_category": "volatility_upshift",
        "transition_dimension": "volatility"
      }
    ],
    "transition_category_count": 8,
    "worst_transition_category": {
      "event_count": 3,
      "metric_value": 0.017333333333333336,
      "transition_category": "recovery_onset",
      "transition_dimension": "drawdown_recovery"
    }
  },
  "worst_regime": {
    "coverage_status": "sufficient",
    "metric_value": 0.015,
    "observation_count": 2,
    "regime_label": "volatility=low_volatility|trend=uptrend|drawdown_recovery=recovery|stress=correlation_stress"
  }
}